Workbook

Sheet Raw Data
A1: Bank | B1: Metric | C1: FY25 | D1: FY26 | E1: Unit | F1: Source
A2: ICICI Bank | B2: Net Profit | C2: 47227 | D2: 50147 | E2: ₹ crore | F2: ICICI Bank FY26 Annual Report
A3: ICICI Bank | B3: Net Interest Income (NII) | C3: 81165 | D3: 88075 | E3: ₹ crore
A4: ICICI Bank | B4: ROA | C4: 2.4 | D4: 2.32 | E4: %
A5: ICICI Bank | B5: ROE | C5: 17.95 | D5: 15.97 | E5: %
A6: ICICI Bank | B6: GNPA | C6: 1.67 | D6: 1.4 | E6: %
A7: ICICI Bank | B7: NNPA | C7: 0.39 | D7: 0.33 | E7: %
A8: ICICI Bank | B8: Cost-to-Income Ratio | C8: 38.64 | D8: 39.75 | E8: %
A9: HDFC Bank | B9: Net Profit | C9: 67347.4 | D9: 74671.3 | E9: ₹ crore | F9: HDFC Bank FY26 Annual Report
A10: HDFC Bank | B10: Net Interest Income (NII) | C10: 122670.1 | D10: 128686 | E10: ₹ crore
A11: HDFC Bank | B11: ROA | C11: 1.91 | D11: 1.94 | E11: %
A12: HDFC Bank | B12: ROE | C12: 14.56 | D12: 14.3 | E12: %
A13: HDFC Bank | B13: GNPA | C13: 1.33 | D13: 1.15 | E13: %
A14: HDFC Bank | B14: NNPA | C14: 0.43 | D14: 0.38 | E14: %
A15: HDFC Bank | B15: Cost-to-Income Ratio | C15: 40.5 | D15: 38 | E15: %
A16: Axis Bank | B16: Net Profit | C16: 26373 | D16: 24457 | E16: ₹ crore | F16: Axis Bank FY26 Annual Report
A17: Axis Bank | B17: Net Interest Income (NII) | C17: 54348 | D17: 56048 | E17: ₹ crore
A18: Axis Bank | B18: ROA | C18: 1.74 | D18: 1.45 | E18: %
A19: Axis Bank | B19: ROE | C19: 16.52 | D19: 13.15 | E19: %
A20: Axis Bank | B20: GNPA | C20: 1.28 | D20: 1.23 | E20: %
A21: Axis Bank | B21: NNPA | C21: 0.33 | D21: 0.37 | E21: %
A22: Axis Bank | B22: Cost-to-Income Ratio | C22: 47.1 | D22: 47.9 | E22: %
A23: SBI | B23: Net Profit | C23: 70901 | D23: 80032 | E23: ₹ crore | F23: SBI Bank FY26 Annual Report
A24: SBI | B24: Net Interest Income (NII) | C24: 166340 | D24: 173120 | E24: ₹ crore
A25: SBI | B25: ROA | C25: 1.1 | D25: 1.12 | E25: %
A26: SBI | B26: ROE | C26: 19.87 | D26: 18.57 | E26: %
A27: SBI | B27: GNPA | C27: 1.82 | D27: 1.49 | E27: %
A28: SBI | B28: NNPA | C28: 0.47 | D28: 0.39 | E28: %
A29: SBI | B29: Cost-to-Income Ratio | C29: 51.64 | D29: 50.11 | E29: %

Sheet Analysis
A1: Bank | B1: Net Profit FY25 (₹ Cr) | C1: Net Profit FY26 (₹ Cr) | D1: NII FY25 (₹ Cr) | E1: NII FY26 (₹ Cr) | F1: ROA FY25 (%) | G1: ROA FY26 (%) | H1: ROE FY25 (%) | I1: ROE FY26 (%) | J1: GNPA FY25 (%) | K1: GNPA FY26 (%) | L1: NNPA FY25 (%) | M1: NNPA FY26 (%) | N1: Cost-to-Income FY25 (%) | O1: Cost-to-Income FY26 (%)
A2: ='Raw Data'!A2 -> ICICI Bank | B2: ='Raw Data'!C2 -> 47227 | C2: ='Raw Data'!D2 -> 50147 | D2: ='Raw Data'!C3 -> 81165 | E2: ='Raw Data'!D3 -> 88075 | F2: ='Raw Data'!C4 -> 2.4 | G2: ='Raw Data'!D4 -> 2.32 | H2: ='Raw Data'!C5 -> 17.95 | I2: ='Raw Data'!D5 -> 15.97 | J2: ='Raw Data'!C6 -> 1.67 | K2: ='Raw Data'!D6 -> 1.4 | L2: ='Raw Data'!C7 -> 0.39 | M2: ='Raw Data'!D7 -> 0.33 | N2: ='Raw Data'!C8 -> 38.64 | O2: ='Raw Data'!D8 -> 39.75
A3: ='Raw Data'!A9 -> HDFC Bank | B3: ='Raw Data'!C9 -> 67347.4 | C3: ='Raw Data'!D9 -> 74671.3 | D3: ='Raw Data'!C10 -> 122670.1 | E3: ='Raw Data'!D10 -> 128686 | F3: ='Raw Data'!C11 -> 1.91 | G3: ='Raw Data'!D11 -> 1.94 | H3: ='Raw Data'!C12 -> 14.56 | I3: ='Raw Data'!D12 -> 14.3 | J3: ='Raw Data'!C13 -> 1.33 | K3: ='Raw Data'!D13 -> 1.15 | L3: ='Raw Data'!C14 -> 0.43 | M3: ='Raw Data'!D14 -> 0.38 | N3: ='Raw Data'!C15 -> 40.5 | O3: ='Raw Data'!D15 -> 38
A4: ='Raw Data'!A16 -> Axis Bank | B4: ='Raw Data'!C16 -> 26373 | C4: ='Raw Data'!D16 -> 24457 | D4: ='Raw Data'!C17 -> 54348 | E4: ='Raw Data'!D17 -> 56048 | F4: ='Raw Data'!C18 -> 1.74 | G4: ='Raw Data'!D18 -> 1.45 | H4: ='Raw Data'!C19 -> 16.52 | I4: ='Raw Data'!D19 -> 13.15 | J4: ='Raw Data'!C20 -> 1.28 | K4: ='Raw Data'!D20 -> 1.23 | L4: ='Raw Data'!C21 -> 0.33 | M4: ='Raw Data'!D21 -> 0.37 | N4: ='Raw Data'!C22 -> 47.1 | O4: ='Raw Data'!D22 -> 47.9
A5: ='Raw Data'!A23 -> SBI | B5: ='Raw Data'!C23 -> 70901 | C5: ='Raw Data'!D23 -> 80032 | D5: ='Raw Data'!C24 -> 166340 | E5: ='Raw Data'!D24 -> 173120 | F5: ='Raw Data'!C25 -> 1.1 | G5: ='Raw Data'!D25 -> 1.12 | H5: ='Raw Data'!C26 -> 19.87 | I5: ='Raw Data'!D26 -> 18.57 | J5: ='Raw Data'!C27 -> 1.82 | K5: ='Raw Data'!D27 -> 1.49 | L5: ='Raw Data'!C28 -> 0.47 | M5: ='Raw Data'!D28 -> 0.39 | N5: ='Raw Data'!C29 -> 51.64 | O5: ='Raw Data'!D29 -> 50.11

Sheet Performance
A1: Bank | B1: Net Profit FY25 (₹ Cr) | C1: Net Profit FY26 (₹ Cr) | D1: Net Profit Growth (%) | E1: NII FY25 (₹ Cr) | F1: NII FY26 (₹ Cr) | G1: NII Growth (%)
A2: =Analysis!A2 -> ICICI Bank | B2: =Analysis!B2 -> 47227 | C2: =Analysis!C2 -> 50147 | D2: =(Performance!C2-Performance!B2)/Performance!B2*100 -> 6.1829038 | E2: =Analysis!D2 -> 81165 | F2: =Analysis!E2 -> 88075 | G2: =(F2-E2)/E2*100 -> 8.5135218
A3: =Analysis!A3 -> HDFC Bank | B3: =Analysis!B3 -> 67347.4 | C3: =Analysis!C3 -> 74671.3 | D3: =(Performance!C3-Performance!B3)/Performance!B3*100 -> 10.874807 | E3: =Analysis!D3 -> 122670.1 | F3: =Analysis!E3 -> 128686 | G3: =(F3-E3)/E3*100 -> 4.904129
A4: =Analysis!A4 -> Axis Bank | B4: =Analysis!B4 -> 26373 | C4: =Analysis!C4 -> 24457 | D4: =(Performance!C4-Performance!B4)/Performance!B4*100 -> -7.2650059 | E4: =Analysis!D4 -> 54348 | F4: =Analysis!E4 -> 56048 | G4: =(F4-E4)/E4*100 -> 3.12799
A5: =Analysis!A5 -> SBI | B5: =Analysis!B5 -> 70901 | C5: =Analysis!C5 -> 80032 | D5: =(Performance!C5-Performance!B5)/Performance!B5*100 -> 12.878521 | E5: =Analysis!D5 -> 166340 | F5: =Analysis!E5 -> 173120 | G5: =(F5-E5)/E5*100 -> 4.0759889
A8: Bank | B8: ROA Rank | C8: ROE Rank | D8: GNPA Rank | E8: NNPA Rank | F8: Cost-to-Income Rank | G8: Profit Growth Rank | H8: NII Growth Rank | I8: Overall Score
A9: ICICI Bank | B9: =_xlfn.RANK.EQ(Analysis!G2,Analysis!$G$2:$G$5,0) -> 1 | C9: =_xlfn.RANK.EQ(Analysis!I2,Analysis!$I$2:$I$5,0) -> 2 | D9: =_xlfn.RANK.EQ(Analysis!K2,Analysis!$K$2:$K$5,1) -> 3 | E9: =_xlfn.RANK.EQ(Analysis!M2,Analysis!$M$2:$M$5,1) -> 1 | F9: =_xlfn.RANK.EQ(Analysis!O2,Analysis!$O$2:$O$5,1) -> 2 | G9: =_xlfn.RANK.EQ(D2,$D$2:$D$5,0) -> 3 | H9: =_xlfn.RANK.EQ(G2,$G$2:$G$5,0) -> 1 | I9: =SUM(B9:H9) -> 13
A10: HDFC Bank | B10: =_xlfn.RANK.EQ(Analysis!G3,Analysis!$G$2:$G$5,0) -> 2 | C10: =_xlfn.RANK.EQ(Analysis!I3,Analysis!$I$2:$I$5,0) -> 3 | D10: =_xlfn.RANK.EQ(Analysis!K3,Analysis!$K$2:$K$5,1) -> 1 | E10: =_xlfn.RANK.EQ(Analysis!M3,Analysis!$M$2:$M$5,1) -> 3 | F10: =_xlfn.RANK.EQ(Analysis!O3,Analysis!$O$2:$O$5,1) -> 1 | G10: =_xlfn.RANK.EQ(D3,$D$2:$D$5,0) -> 2 | H10: =_xlfn.RANK.EQ(G3,$G$2:$G$5,0) -> 2 | I10: =SUM(B10:H10) -> 14
A11: Axis Bank | B11: =_xlfn.RANK.EQ(Analysis!G4,Analysis!$G$2:$G$5,0) -> 3 | C11: =_xlfn.RANK.EQ(Analysis!I4,Analysis!$I$2:$I$5,0) -> 4 | D11: =_xlfn.RANK.EQ(Analysis!K4,Analysis!$K$2:$K$5,1) -> 2 | E11: =_xlfn.RANK.EQ(Analysis!M4,Analysis!$M$2:$M$5,1) -> 2 | F11: =_xlfn.RANK.EQ(Analysis!O4,Analysis!$O$2:$O$5,1) -> 3 | G11: =_xlfn.RANK.EQ(D4,$D$2:$D$5,0) -> 4 | H11: =_xlfn.RANK.EQ(G4,$G$2:$G$5,0) -> 4 | I11: =SUM(B11:H11) -> 22
A12: SBI | B12: =_xlfn.RANK.EQ(Analysis!G5,Analysis!$G$2:$G$5,0) -> 4 | C12: =_xlfn.RANK.EQ(Analysis!I5,Analysis!$I$2:$I$5,0) -> 1 | D12: =_xlfn.RANK.EQ(Analysis!K5,Analysis!$K$2:$K$5,1) -> 4 | E12: =_xlfn.RANK.EQ(Analysis!M5,Analysis!$M$2:$M$5,1) -> 4 | F12: =_xlfn.RANK.EQ(Analysis!O5,Analysis!$O$2:$O$5,1) -> 4 | G12: =_xlfn.RANK.EQ(D5,$D$2:$D$5,0) -> 1 | H12: =_xlfn.RANK.EQ(G5,$G$2:$G$5,0) -> 3 | I12: =SUM(B12:H12) -> 21

Sheet Charts
A42: Bank | B42: ROA FY26 (%) | C42: ROE FY26 (%)
A43: ICICI Bank | B43: =Analysis!G2 -> 2.32 | C43: =Analysis!I2 -> 15.97
A44: HDFC Bank | B44: =Analysis!G3 -> 1.94 | C44: =Analysis!I3 -> 14.3
A45: Axis Bank | B45: =Analysis!G4 -> 1.45 | C45: =Analysis!I4 -> 13.15
A46: SBI | B46: =Analysis!G5 -> 1.12 | C46: =Analysis!I5 -> 18.57
A49: Bank | B49: GNPA FY26 (%) | C49: NNPA FY26 (%)
A50: ICICI Bank | B50: =Analysis!K2 -> 1.4 | C50: =Analysis!M2 -> 0.33
A51: HDFC Bank | B51: =Analysis!K3 -> 1.15 | C51: =Analysis!M3 -> 0.38
A52: Axis Bank | B52: =Analysis!K4 -> 1.23 | C52: =Analysis!M4 -> 0.37
A53: SBI | B53: =Analysis!K5 -> 1.49 | C53: =Analysis!M5 -> 0.39

Sheet Key Findings
A1: No. | B1: Key Finding | C1: Evidence and Interpretation
A2: 1 | B2: Strongest profit growth | C2: SBI recorded FY26 net profit of ₹80,032 crore and profit growth of 12.88%, the highest among the four banks. Absolute profit does not directly measure efficiency.
A3: 2 | B3: Highest NII growth | C3: ICICI's NII grew by 8.51%, from ₹81,165 crore to ₹88,075 crore, the highest growth in the group.
A4: 3 | B4: Strong asset quality and efficiency | C4: HDFC had the lowest FY26 GNPA at 1.15% and lowest cost-to-income ratio at 38.00%. Its GNPA, NNPA and cost-to-income ratio improved from FY25.
A5: 4 | B5: ICICI's profitability strengths | C5: ICICI had the highest FY26 ROA at 2.32% and lowest NNPA at 0.33%, but ROA declined and cost-to-income increased year over year.
A6: 5 | B6: SBI's mixed performance | C6: SBI had the highest ROE at 18.57%, but the lowest ROA at 1.12% and highest GNPA and NNPA ratios among the four banks.
A7: 6 | B7: Axis's declining profit | C7: Axis net profit declined by 7.27% despite NII growth of 3.13%. ROA and ROE also declined; further data is needed to determine the reasons.
A8: 7 | B8: Overall ranking | C8: ICICI ranked first with 13 points, followed by HDFC at 14, SBI at 21 and Axis at 22. The score uses equal weighting for seven rankings and is not a universal measure of bank quality.
